{
    "version": 2,
    "settings": {
        "appearanceTools": true,
        "layout": {
            "contentSize": "732px",
            "wideSize": "1100px"
        },
        "typography": {
            "fluid": true,
            "fontSizes": [
                {
                    "fluid": false,
                    "slug": "tiny",
                    "size": "0.8125rem",
                    "name": "Tiny"
                },
                {
                    "fluid": false,
                    "slug": "extra-small",
                    "size": "0.875rem",
                    "name": "Extra Small"
                },
                {
                    "fluid": false,
                    "slug": "small",
                    "size": "0.9375rem",
                    "name": "Small"
                },
                {
                    "slug": "normal",
                    "size": "clamp(1.0625rem, 1.0625rem + ((1vw - 0.48rem) * 0.12), 1.125rem)",
                    "fluid": {
                        "min": "1.0625rem",
                        "max": "1.125rem"
                    },
                    "name": "Normal"
                },
                {
                    "slug": "large",
                    "size": "clamp(1.15625rem, 1.15625rem + ((1vw - 0.48rem) * 0.18), 1.25rem)",
                    "fluid": {
                        "min": "1.15625rem",
                        "max": "1.25rem"
                    },
                    "name": "Large"
                },
                {
                    "slug": "medium-large",
                    "size": "clamp(2.25rem, 2.25rem + ((1vw - 0.48rem) * 1.683), 3.125rem)",
                    "fluid": {
                        "min": "2.25rem",
                        "max": "3.125rem"
                    },
                    "name": "Medium Large"
                },
                {
                    "slug": "extra-large",
                    "size": "clamp(2.625rem, 2.625rem + ((1vw - 0.48rem) * 2.885), 4.125rem)",
                    "fluid": {
                        "min": "2.625rem",
                        "max": "4.125rem"
                    },
                    "name": "Extra large"
                },
                {
                    "slug": "huge",
                    "size": "clamp(3.125rem, 3.125rem + ((1vw - 0.48rem) * 3.606), 5rem)",
                    "fluid": {
                        "min": "3.125rem",
                        "max": "5rem"
                    },
                    "name": "Huge"
                }
            ],
            "fontFamilies": [
                {
                    "fontFamily": "-apple-system,BlinkMacSystemFont,\"Segoe UI\",Roboto,Oxygen-Sans,Ubuntu,Cantarell,\"Helvetica Neue\",sans-serif",
                    "name": "System Font",
                    "slug": "system-font"
                },
                {
                    "fontFamily": "\"Bitter\", sans-serif",
                    "name": "Bitter Font",
                    "slug": "bitter-font",
                    "fontFace": [
                        {
                            "fontFamily": "Bitter",
                            "fontWeight": "100 900",
                            "fontStyle": "normal",
                            "fontStretch": "normal",
                            "src": [
                                "file:./assets/fonts/bitter/bitter-variable-font-wght.ttf"
                            ]
                        },
						{
                            "fontFamily": "Bitter",
                            "fontWeight": "100 900",
                            "fontStyle": "italic",
                            "fontStretch": "normal",
                            "src": [
                                "file:./assets/fonts/bitter/bitter-italic-variable-font-wght.ttf"
                            ]
						}
                    ]
                },
                {
                    "fontFamily": "\"Inter\", sans-serif",
                    "name": "Inter Font",
                    "slug": "inter-font",
                    "fontFace": [
                        {
                            "fontFamily": "Inter",
                            "fontWeight": "100 900",
                            "fontStyle": "normal",
                            "fontStretch": "normal",
                            "src": [
                                "file:./assets/fonts/inter/inter-variable-font-wght.ttf"
                            ]
                        }
                    ]
                },
                {
                    "fontFamily": "\"Manrope\", sans-serif",
                    "name": "Manrope Font",
                    "slug": "manrope-font",
                    "fontFace": [
                        {
                            "fontFamily": "Manrope",
                            "fontWeight": "200 800",
                            "fontStyle": "normal",
                            "fontStretch": "normal",
                            "src": [
                                "file:./assets/fonts/manrope/manrope-variable-font-wght.ttf"
                            ]
                        }
                    ]
                },
                {
                    "fontFamily": "\"Nunito\", sans-serif",
                    "name": "Nunito Font",
                    "slug": "nunito-font",
                    "fontFace": [
                        {
                            "fontFamily": "Nunito",
                            "fontWeight": "200 900",
                            "fontStyle": "normal",
                            "fontStretch": "normal",
                            "src": [
                                "file:./assets/fonts/nunito/nunito-variable-font-wght.ttf"
                            ]
                        },
						{
                            "fontFamily": "Nunito",
                            "fontWeight": "200 900",
                            "fontStyle": "italic",
                            "fontStretch": "normal",
                            "src": [
                                "file:./assets/fonts/nunito/nunito-italic-variable-font-wght.ttf"
                            ]
						}
                    ]
                },
                {
                    "fontFamily": "\"Outfit\", sans-serif",
                    "name": "Outfit Font",
                    "slug": "outfit-font",
                    "fontFace": [
                        {
                            "fontFamily": "Outfit",
                            "fontWeight": "100 900",
                            "fontStyle": "normal",
                            "fontStretch": "normal",
                            "src": [
                                "file:./assets/fonts/outfit/outfit-variable-font-wght.ttf"
                            ]
                        }
                    ]
                },
                {
                    "fontFamily": "\"Open Sans\", sans-serif",
                    "name": "Open Sans Font",
                    "slug": "opensans-font",
                    "fontFace": [
                        {
                            "fontFamily": "Open Sans",
                            "fontWeight": "300 800",
                            "fontStyle": "normal",
                            "fontStretch": "normal",
                            "src": [
                                "file:./assets/fonts/open-sans/opensans-variable-font-wght.ttf"
                            ]
                        },
						{
                            "fontFamily": "Open Sans",
                            "fontWeight": "300 800",
                            "fontStyle": "italic",
                            "fontStretch": "normal",
                            "src": [
                                "file:./assets/fonts/open-sans/opensans-italic-variable-font-wght.ttf"
                            ]
						}
                    ]
                },
                {
                    "fontFamily": "\"Playfair Display\", sans-serif",
                    "name": "Playfair Display Font",
                    "slug": "playfairdisplay-font",
                    "fontFace": [
                        {
                            "fontFamily": "Playfair Display",
                            "fontWeight": "400 900",
                            "fontStyle": "normal",
                            "fontStretch": "normal",
                            "src": [
                                "file:./assets/fonts/playfair-display/playfairdisplay-variable-font-wght.ttf"
                            ]
                        },
						{
                            "fontFamily": "Playfair Display",
                            "fontWeight": "400 900",
                            "fontStyle": "italic",
                            "fontStretch": "normal",
                            "src": [
                                "file:./assets/fonts/playfair-display/playfairdisplay-italic-variable-font-wght.ttf"
                            ]
						}
                    ]
                },
                {
                    "fontFamily": "\"Plus Jakarta Sans\", sans-serif",
                    "name": "Plus Jakarta Sans",
                    "slug": "plusjakartasans-font",
                    "fontFace": [
                        {
                            "fontFamily": "Plus Jakarta Sans",
                            "fontWeight": "200 800",
                            "fontStyle": "normal",
                            "fontStretch": "normal",
                            "src": [
                                "file:./assets/fonts/plus-jakarta-sans/plusjakartasans-variable-font-wght.ttf"
                            ]
                        },
						{
                            "fontFamily": "Plus Jakarta Sans",
                            "fontWeight": "200 800",
                            "fontStyle": "italic",
                            "fontStretch": "normal",
                            "src": [
                                "file:./assets/fonts/plus-jakarta-sans/plusjakartasans-italic-variable-font-wght.ttf"
                            ]
						}
                    ]
                },
                {
                    "fontFamily": "\"Roboto Slab\", sans-serif",
                    "name": "Roboto Slab Font",
                    "slug": "robotoslab-font",
                    "fontFace": [
                        {
                            "fontFamily": "Roboto Slab",
                            "fontWeight": "100 900",
                            "fontStyle": "normal",
                            "fontStretch": "normal",
                            "src": [
                                "file:./assets/fonts/roboto-slab/robotoslab-variable-font-wght.ttf"
                            ]
                        }
                    ]
                },
                {
                    "fontFamily": "\"Urbanist\", sans-serif",
                    "name": "Urbanist Font",
                    "slug": "urbanist-font",
                    "fontFace": [
                        {
                            "fontFamily": "Urbanist",
                            "fontWeight": "100 900",
                            "fontStyle": "normal",
                            "fontStretch": "normal",
                            "src": [
                                "file:./assets/fonts/urbanist/urbanist-variable-font-wght.ttf"
                            ]
                        },
						{
                            "fontFamily": "Urbanist",
                            "fontWeight": "100 900",
                            "fontStyle": "italic",
                            "fontStretch": "normal",
                            "src": [
                                "file:./assets/fonts/urbanist/urbanist-italic-variable-font-wght.ttf"
                            ]
						}
                    ]
                }
            ]
        },
        "color": {
            "palette": [
                {
                    "slug": "background",
                    "color": "#FFFFFF",
                    "name": "Background"
                },
                {
                    "slug": "primary",
                    "color": "#0DA88C",
                    "name": "Primary"
                },
                {
                    "slug": "secondary",
                    "color": "#21222F",
                    "name": "Secondary"
                },
                {
                    "slug": "tertiary",
                    "color": "#484952",
                    "name": "Tertiary"
                },
                {
                    "slug": "quaternary",
                    "color": "#E2F2EF",
                    "name": "Quaternary"
                },
                {
                    "slug": "quinary",
                    "color": "#F6B642",
                    "name": "Quinary"
                },
                {
                    "slug": "senary",
                    "color": "#015D61",
                    "name": "Senary"
                },
                {
                    "slug": "light-gray",
                    "color": "rgba(37,39,64,0.25)",
                    "name": "Light gray"
                }
            ]
        },
        "spacing": {
            "spacingSizes": [
                {
                    "slug": "small",
                    "size": "1.25rem",
                    "name": "Small"
                },
                {
                    "slug": "normal",
                    "size": "clamp(1.5625rem, 1.5625rem + ((1vw - 0.48rem) * 3.005), 3.125rem)",
                    "name": "Normal"
                },
                {
                    "slug": "medium",
                    "size": "clamp(4.6875rem, 4.6875rem + ((1vw - 0.48rem) * 9.014), 9.375rem)",
                    "name": "Medium"
                },
                {
                    "slug": "large",
                    "size": "clamp(6.25rem, 6.25rem + ((1vw - 0.48rem) * 12.019), 12.5rem)",
                    "name": "Large"
                },
                {
                    "slug": "extra-large",
                    "size": "clamp(7.8125rem, 7.8125rem + ((1vw - 0.48rem) * 15.024), 15.625rem)",
                    "name": "Extra large"
                },
                {
                    "slug": "huge",
                    "size": "clamp(9.375rem, 9.375rem + ((1vw - 0.48rem) * 18.029), 18.75rem)",
                    "name": "Huge"
                },
                {
                    "slug": "giant",
                    "size": "clamp(15.625rem, 15.625rem + ((1vw - 0.48rem) * 30.048), 31.25rem)",
                    "name": "Giant"
                }
            ]
        },
        "custom": {
            "spacing": {
                "small": "1.25rem",
                "normal": "3.125rem",
                "medium": "clamp(2rem, 8vw,6.25rem)",
                "medium-large": "clamp(3.125rem, 12vw,9.375rem)",
                "large": "clamp(6.25rem, 16vw,12.5rem)",
                "navigation":"clamp(2rem, 2rem + ((1vw - 0.48rem) * 3.846), 4rem)"
            },
            "typography": {
                "font-size": {
                    "hone": "clamp(2.25rem, 2.25rem + ((1vw - 0.48rem) * 1.683), 3.125rem)",
                    "htwo": "clamp(1.9375rem, 1.9375rem + ((1vw - 0.48rem) * 1.563), 2.75rem)",
                    "hthree": "clamp(1.6875rem, 1.6875rem + ((1vw - 0.48rem) * 1.082), 2.25rem)",
                    "hfour": "clamp(1.5rem, 1.5rem + ((1vw - 0.48rem) * 0.24), 1.625rem)",
                    "hfive": "clamp(1.3125rem, 1.3125rem + ((1vw - 0.48rem) * 0.12), 1.375rem)",
                    "hsix": "1.125rem",
                    "p": "1rem",
                    "post-page-title": "clamp(3.125rem, 3.125rem + ((1vw - 0.48rem) * 3.365), 4.875rem)",
                    "post-title": "1.8125rem",
                    "navigation":"1.0625rem"
                },
                "line-height": {
                    "hone": "1.4",
                    "htwo": "1.4",
                    "hthree": "1.4",
                    "hfour": "1.46",
                    "hfive": "1.45",
                    "hsix": "1.44",
                    "p": "1.875",
                    "post-title": "1.6",
                    "navigation":"1.24",
                    "tiny":"1.7",
                    "extra-small":"1.7",
                    "small": "1.8",
                    "normal":"1.9",
                    "large":"1.9",
                    "medium-large":"1.4",
                    "extra-large":"1.3",
                    "huge":"1.2",
                    "button":"1"
                },
                "font-weight": {
                    "normal": 400,
                    "medium": 500,
                    "semi-bold": 600,
                    "bold": 700,
                    "heading":500,
                    "button":500,
                    "huge":600
                },
                "font-family": {
                    "primary": "var(--wp--preset--font-family--outfit-font)",
                    "secondary": "var(--wp--preset--font-family--inter-font)"
                }
            },
            "color": {
                "navigation-text":"var(--wp--preset--color--secondary)",
                "navigation-link-hover":"var(--wp--preset--color--primary)"
            }
        }
    },
    "styles": {
        "elements": {
            "link": {
				"color": {
                    "text": "var(--wp--preset--color--secondary)"
                },
                "typography": {
					"textDecoration": "underline"
				},
				":hover": {
                    "color": {
                        "text": "var(--wp--preset--color--primary)"
                    },
					"typography": {
						"textDecoration": "none"
					}
				}
			},
            "h1": {
                "typography": {
                    "fontSize": "var(--wp--custom--typography--font-size--hone)",
                    "lineHeight": "var(--wp--custom--typography--line-height--hone)"
                }
            },
            "h2": {
                "typography": {
                    "fontSize": "var(--wp--custom--typography--font-size--htwo)",
                    "lineHeight": "var(--wp--custom--typography--line-height--htwo)"
                }
            },
            "h3": {
                "typography": {
                    "fontSize": "var(--wp--custom--typography--font-size--hthree)",
                    "lineHeight": "var(--wp--custom--typography--line-height--hthree)"
                }
            },
            "h4": {
                "typography": {
                    "fontSize": "var(--wp--custom--typography--font-size--hfour)",
                    "lineHeight": "var(--wp--custom--typography--line-height--hfour)"
                }
            },
            "h5": {
                "typography": {
                    "fontSize": "var(--wp--custom--typography--font-size--hfive)",
                    "lineHeight": "var(--wp--custom--typography--line-height--hfive)"
                }
            },
            "h6": {
                "typography": {
                    "fontSize": "var(--wp--custom--typography--font-size--hsix)",
                    "lineHeight": "var(--wp--custom--typography--line-height--hsix)"
                }
            }
        },
        "blocks": {
            "core/cover": {
                "spacing": {
                    "padding": {
                        "top": "1.25rem",
                        "bottom": "1.25rem",
                        "left": "1.25rem",
                        "right": "1.25rem"
                    }
                }
            },
            "core/quote": {
                "border": {
                    "width": "0 0 0 4px",
                    "color": "var(--wp--preset--color--primary)"
                },
                "typography": {
                    "fontFamily": "var(--wp--custom--typography--font-family--secondary)",
                    "fontWeight": "light"
                }
            },
            "core/button": {
                "border": {
                    "radius": "0"
                },
                "color": {
                    "background": "var(--wp--preset--color--primary)",
                    "text": "var(--wp--preset--color--background)"
                },
                "typography": {
                    "fontFamily": "var(--wp--custom--typography--font-family--primary)",
                    "lineHeight": "1.4",
                    "fontWeight": "var(--wp--custom--typography--font-weight--bold)",
                    "textDecoration": "none"
                }
            },
            "core/navigation": {
                "color": {
                    "text": "var(--wp--preset--color--secondary)"
                },
                "typography": {
                    "fontSize": "var(--wp--preset--typography--font-size--small)",
                    "fontFamily": "var(--wp--custom--typography--font-family--primary)",
                    "lineHeight": "1.2",
                    "fontWeight": "var(--wp--custom--typography--font-weight--semi-bold)"
                }
            },
            "core/site-title": {
                "color": {
                    "text": "var(--wp--preset--color--secondary)"
                },
                "typography": {
                    "fontSize": "var(--wp--custom--typography--font-size--hthree)",
                    "fontFamily": "var(--wp--custom--typography--font-family--primary)",
                    "lineHeight": "var(--wp--custom--typography--line-height--hthree)",
                    "fontWeight": "var(--wp--custom--typography--font-weight--semi-bold)"
                }
            },
            "core/heading": {
                "spacing": {
                    "margin": {
                        "top": "5px",
                        "bottom": "5px"
                    }
                },
                "color": {
                    "text": "var(--wp--preset--color--secondary)"
                },
                "typography": {
                    "fontFamily": "var(--wp--custom--typography--font-family--primary)",
                    "fontWeight": "var(--wp--custom--typography--font-weight--semi-bold)",
                    "letterSpacing": "-0.01em"
                }
            },
            "core/paragraph": {
                "spacing": {
                    "margin": {
                        "top": "0px"
                    }
                }
            },
            "core/post-terms": {
                "color": {
                    "text": "var(--wp--preset--color--tertiary)"
                },
                "typography": {
                    "fontSize": "0.9375rem",
                    "fontFamily": "var(--wp--custom--typography--font-family--secondary)",
                    "lineHeight": "1.9",
                    "fontWeight": "400"
                }
            },
            "core/post-title": {
                "color": {
                    "text": "var(--wp--preset--color--secondary)"
                },
                "typography": {
                    "fontSize": "var(--wp--custom--typography--font-size--post-title)",
                    "lineHeight": "var(--wp--custom--typography--line-height--post-title)",
                    "fontWeight": "var(--wp--custom--typography--font-weight--semi-bold)",
                    "fontFamily": "var(--wp--custom--typography--font-family--primary)"
                }
            },
            "core/post-author": {
                "color": {
                    "text": "var(--wp--preset--color--secondary)"
                },
                "typography": {
                    "fontSize": "0.9375rem",
                    "fontFamily": "var(--wp--custom--typography--font-family--secondary)",
                    "lineHeight": "1.9",
                    "fontWeight": "400"
                }
            },
            "core/post-date": {
                "color": {
                    "text": "var(--wp--preset--color--secondary)"
                },
                "typography": {
                    "fontSize": "0.9375rem",
                    "fontFamily": "var(--wp--custom--typography--font-family--secondary)",
                    "lineHeight": "1.9",
                    "fontWeight": "400"
                }
            },
            "core/post-navigation-link": {
                "color": {
                    "text": "var(--wp--preset--color--secondary)"
                },
                "typography": {
                    "fontSize": "var(--wp--preset--typography--font-size--p)",
                    "fontFamily": "var(--wp--custom--typography--font-family--secondary)",
                    "lineHeight": "1.7",
                    "fontWeight": "400"
                }
            },
            "core/post-comments": {
                "color": {
                    "text": "var(--wp--preset--color--secondary)"
                },
                "typography": {
                    "fontSize": "var(--wp--preset--typography--font-size--small)",
                    "fontFamily": "var(--wp--custom--typography--font-family--secondary)",
                    "lineHeight": "var(--wp--preset--typography--line-height--small)",
                    "fontWeight": "400"
                }
            }
        },
        "spacing": {
            "blockGap": "1.5rem"
        },
        "color": {
            "background": "var(--wp--preset--color--background)",
            "text": "var(--wp--preset--color--tertiary)"
        },
        "typography": {
            "fontFamily": "var(--wp--custom--typography--font-family--secondary)",
            "lineHeight": "var(--wp--custom--typography--line-height--p)",
            "fontSize": "var(--wp--custom--typography--font-size--p)"
        },
        "typography": {
            "fluid": true,
            "fontSizes": [
                {
                    "fluid": false,
                    "slug": "tiny",
                    "size": "0.8125rem",
                    "name": "Tiny"
                },
                {
                    "fluid": false,
                    "slug": "extra-small",
                    "size": "0.875rem",
                    "name": "Extra Small"
                },
                {
                    "fluid": false,
                    "slug": "small",
                    "size": "0.9375rem",
                    "name": "Small"
                },
                {
                    "slug": "normal",
                    "size": "clamp(1.0625rem, 1.0625rem + ((1vw - 0.48rem) * 0.12), 1.125rem)",
                    "fluid": {
                        "min": "1.0625rem",
                        "max": "1.125rem"
                    },
                    "name": "Normal"
                },
                {
                    "slug": "large",
                    "size": "clamp(1.15625rem, 1.15625rem + ((1vw - 0.48rem) * 0.18), 1.25rem)",
                    "fluid": {
                        "min": "1.15625rem",
                        "max": "1.25rem"
                    },
                    "name": "Large"
                },
                {
                    "slug": "medium-large",
                    "size": "clamp(2.25rem, 2.25rem + ((1vw - 0.48rem) * 1.683), 3.125rem)",
                    "fluid": {
                        "min": "2.25rem",
                        "max": "3.125rem"
                    },
                    "name": "Medium Large"
                },
                {
                    "slug": "extra-large",
                    "size": "clamp(2.625rem, 2.625rem + ((1vw - 0.48rem) * 2.885), 4.125rem)",
                    "fluid": {
                        "min": "2.625rem",
                        "max": "4.125rem"
                    },
                    "name": "Extra large"
                },
                {
                    "slug": "huge",
                    "size": "clamp(3.125rem, 3.125rem + ((1vw - 0.48rem) * 3.606), 5rem)",
                    "fluid": {
                        "min": "3.125rem",
                        "max": "5rem"
                    },
                    "name": "Huge"
                }
            ],
            "fontFamilies": [
                {
                    "fontFamily": "-apple-system,BlinkMacSystemFont,\"Segoe UI\",Roboto,Oxygen-Sans,Ubuntu,Cantarell,\"Helvetica Neue\",sans-serif",
                    "name": "System Font",
                    "slug": "system-font"
                },
                {
                    "fontFamily": "\"Bitter\", sans-serif",
                    "name": "Bitter Font",
                    "slug": "bitter-font",
                    "fontFace": [
                        {
                            "fontFamily": "Bitter",
                            "fontWeight": "100 900",
                            "fontStyle": "normal",
                            "fontStretch": "normal",
                            "src": [
                                "file:./assets/fonts/bitter/bitter-variable-font-wght.ttf"
                            ]
                        },
						{
                            "fontFamily": "Bitter",
                            "fontWeight": "100 900",
                            "fontStyle": "italic",
                            "fontStretch": "normal",
                            "src": [
                                "file:./assets/fonts/bitter/bitter-italic-variable-font-wght.ttf"
                            ]
						}
                    ]
                },
                {
                    "fontFamily": "\"Inter\", sans-serif",
                    "name": "Inter Font",
                    "slug": "inter-font",
                    "fontFace": [
                        {
                            "fontFamily": "Inter",
                            "fontWeight": "100 900",
                            "fontStyle": "normal",
                            "fontStretch": "normal",
                            "src": [
                                "file:./assets/fonts/inter/inter-variable-font-wght.ttf"
                            ]
                        }
                    ]
                },
                {
                    "fontFamily": "\"Manrope\", sans-serif",
                    "name": "Manrope Font",
                    "slug": "manrope-font",
                    "fontFace": [
                        {
                            "fontFamily": "Manrope",
                            "fontWeight": "200 800",
                            "fontStyle": "normal",
                            "fontStretch": "normal",
                            "src": [
                                "file:./assets/fonts/manrope/manrope-variable-font-wght.ttf"
                            ]
                        }
                    ]
                },
                {
                    "fontFamily": "\"Nunito\", sans-serif",
                    "name": "Nunito Font",
                    "slug": "nunito-font",
                    "fontFace": [
                        {
                            "fontFamily": "Nunito",
                            "fontWeight": "200 900",
                            "fontStyle": "normal",
                            "fontStretch": "normal",
                            "src": [
                                "file:./assets/fonts/nunito/nunito-variable-font-wght.ttf"
                            ]
                        },
						{
                            "fontFamily": "Nunito",
                            "fontWeight": "200 900",
                            "fontStyle": "italic",
                            "fontStretch": "normal",
                            "src": [
                                "file:./assets/fonts/nunito/nunito-italic-variable-font-wght.ttf"
                            ]
						}
                    ]
                },
                {
                    "fontFamily": "\"Outfit\", sans-serif",
                    "name": "Outfit Font",
                    "slug": "outfit-font",
                    "fontFace": [
                        {
                            "fontFamily": "Outfit",
                            "fontWeight": "100 900",
                            "fontStyle": "normal",
                            "fontStretch": "normal",
                            "src": [
                                "file:./assets/fonts/outfit/outfit-variable-font-wght.ttf"
                            ]
                        }
                    ]
                },
                {
                    "fontFamily": "\"Open Sans\", sans-serif",
                    "name": "Open Sans Font",
                    "slug": "opensans-font",
                    "fontFace": [
                        {
                            "fontFamily": "Open Sans",
                            "fontWeight": "300 800",
                            "fontStyle": "normal",
                            "fontStretch": "normal",
                            "src": [
                                "file:./assets/fonts/open-sans/opensans-variable-font-wght.ttf"
                            ]
                        },
						{
                            "fontFamily": "Open Sans",
                            "fontWeight": "300 800",
                            "fontStyle": "italic",
                            "fontStretch": "normal",
                            "src": [
                                "file:./assets/fonts/open-sans/opensans-italic-variable-font-wght.ttf"
                            ]
						}
                    ]
                },
                {
                    "fontFamily": "\"Playfair Display\", sans-serif",
                    "name": "Playfair Display Font",
                    "slug": "playfairdisplay-font",
                    "fontFace": [
                        {
                            "fontFamily": "Playfair Display",
                            "fontWeight": "400 900",
                            "fontStyle": "normal",
                            "fontStretch": "normal",
                            "src": [
                                "file:./assets/fonts/playfair-display/playfairdisplay-variable-font-wght.ttf"
                            ]
                        },
						{
                            "fontFamily": "Playfair Display",
                            "fontWeight": "400 900",
                            "fontStyle": "italic",
                            "fontStretch": "normal",
                            "src": [
                                "file:./assets/fonts/playfair-display/playfairdisplay-italic-variable-font-wght.ttf"
                            ]
						}
                    ]
                },
                {
                    "fontFamily": "\"Plus Jakarta Sans\", sans-serif",
                    "name": "Plus Jakarta Sans",
                    "slug": "plusjakartasans-font",
                    "fontFace": [
                        {
                            "fontFamily": "Plus Jakarta Sans",
                            "fontWeight": "200 800",
                            "fontStyle": "normal",
                            "fontStretch": "normal",
                            "src": [
                                "file:./assets/fonts/plus-jakarta-sans/plusjakartasans-variable-font-wght.ttf"
                            ]
                        },
						{
                            "fontFamily": "Plus Jakarta Sans",
                            "fontWeight": "200 800",
                            "fontStyle": "italic",
                            "fontStretch": "normal",
                            "src": [
                                "file:./assets/fonts/plus-jakarta-sans/plusjakartasans-italic-variable-font-wght.ttf"
                            ]
						}
                    ]
                },
                {
                    "fontFamily": "\"Roboto Slab\", sans-serif",
                    "name": "Roboto Slab Font",
                    "slug": "robotoslab-font",
                    "fontFace": [
                        {
                            "fontFamily": "Roboto Slab",
                            "fontWeight": "100 900",
                            "fontStyle": "normal",
                            "fontStretch": "normal",
                            "src": [
                                "file:./assets/fonts/roboto-slab/robotoslab-variable-font-wght.ttf"
                            ]
                        }
                    ]
                },
                {
                    "fontFamily": "\"Urbanist\", sans-serif",
                    "name": "Urbanist Font",
                    "slug": "urbanist-font",
                    "fontFace": [
                        {
                            "fontFamily": "Urbanist",
                            "fontWeight": "100 900",
                            "fontStyle": "normal",
                            "fontStretch": "normal",
                            "src": [
                                "file:./assets/fonts/urbanist/urbanist-variable-font-wght.ttf"
                            ]
                        },
						{
                            "fontFamily": "Urbanist",
                            "fontWeight": "100 900",
                            "fontStyle": "italic",
                            "fontStretch": "normal",
                            "src": [
                                "file:./assets/fonts/urbanist/urbanist-italic-variable-font-wght.ttf"
                            ]
						}
                    ]
                }
            ]
        }
    },
    "templateParts": [
        {
            "name": "header",
            "title": "Header",
            "area": "header"
        },
        {
            "name": "header-with-button",
            "title": "Header with logo, menu and buttons",
            "area": "header"
        },
        {
            "name": "footer",
            "title": "Footer",
            "area": "footer"
        },
        {
            "name": "footer-four-column",
            "title": "Footer (4 Columns)",
            "area": "footer"
        }
    ],
    "customTemplates": [
        {
            "name": "blank",
            "title": "Blank",
            "postTypes": [
                "page",
                "post"
            ]
        },
        {
            "name": "page-with-button-header",
            "title": "Page (Button Header with 4 Column Footer)",
            "postTypes": [
                "page"
            ]
        },
        {
            "name": "single-with--button-header",
            "title": "Single Post (Button Header with 4 Column Footer)",
            "postTypes": [
                "post"
            ]
        },
        {
            "name": "single-with-sidebar",
            "title": "Single Post (with sidebar)",
            "postTypes": [
                "post"
            ]
        }
    ]
}